d2f2/CONFIGURATIONS.py
d2f2/__init__.py
d2f2/__main__.py
d2f2/convert.py
d2f2/shell.py
d2f2-2.1.3.dist-info/LICENSE
d2f2-2.1.3.dist-info/METADATA
d2f2-2.1.3.dist-info/WHEEL
d2f2-2.1.3.dist-info/entry_points.txt
d2f2-2.1.3.dist-info/top_level.txt
d2f2-2.1.3.dist-info/RECORD
