Metadata-Version: 2.1
Name: d2f2
Version: 2.1.3
Summary: Tool to convert image folders into files
Home-page: https://github.com/DomCie/d2f2
Author: DomCie
Author-email: dev@domcie.net
License: UNKNOWN
Platform: UNKNOWN
Classifier: Programming Language :: Python :: 3
Classifier: License :: OSI Approved :: GNU Affero General Public License v3 or later (AGPLv3+)
Classifier: License :: OSI Approved :: GNU General Public License v3 or later (GPLv3+)
Classifier: Operating System :: OS Independent
License-File: LICENSE
Requires-Dist: PyMuPDF (>=1.19)
